ingot_grpclib/__init__.py
ingot_grpclib/bootstrap/__init__.py
ingot_grpclib/bootstrap/base.py
ingot_grpclib/bootstrap/scaffolding/__init__.py
ingot_grpclib/contrib/__init__.py
ingot_grpclib/scripts/__init__.py
ingot_grpclib/scripts/ingot_grpclib.py
ingot_grpclib/tests/__init__.py
ingot_grpclib/tests/functionals/__init__.py
ingot_grpclib/tests/units/__init__.py
ingot_grpclib/tests/units/bootstrap/__init__.py
ingot_grpclib/tests/units/bootstrap/test_base.py
ingot_grpclib/tests/units/contrib/__init__.py
ingot_grpclib/tests/units/scripts/__init__.py
ingot_grpclib/tests/units/scripts/test_ingot_grpclib.py
ingot_grpclib-0.1.0.dist-info/LICENSE
ingot_grpclib-0.1.0.dist-info/METADATA
ingot_grpclib-0.1.0.dist-info/WHEEL
ingot_grpclib-0.1.0.dist-info/entry_points.txt
ingot_grpclib-0.1.0.dist-info/top_level.txt
ingot_grpclib-0.1.0.dist-info/RECORD
