Metadata-Version: 2.1
Name: ingot-grpclib
Version: 0.1.0
Summary: Provides gRPC functionality based on the grpclib package
Home-page: https://github.com/ABKorotky/ingot-grpclib
Author: Alexander Korotkiy
Author-email: abkorotky@gmail.com
License: UNKNOWN
Platform: UNKNOWN
Classifier: Development Status :: 1 - Planning
Classifier: Environment :: Web Environment
Classifier: Framework :: AsyncIO
Classifier: Intended Audience :: Developers
Classifier: License :: OSI Approved :: GNU General Public License (GPL)
Classifier: Natural Language :: English
Classifier: Operating System :: POSIX
Classifier: Operating System :: POSIX :: Linux
Classifier: Programming Language :: Python
Classifier: Programming Language :: Python :: 3.9
Classifier: Topic :: Internet
License-File: LICENSE
Requires-Dist: grpclib (~=0.4.1)
Requires-Dist: ingots (~=0.18.0)
Requires-Dist: protobuf (~=3.17.3)
